<?xml version="1.0" encoding="UTF-8" ?>

<odoo>
    <data>
        <record id="hr_contract_history_view_list" model="ir.ui.view">
            <field name="name">hr.contract.history.list</field>
            <field name="model">hr.contract.history</field>
            <field name="inherit_id" ref="hr_contract.hr_contract_history_view_list"/>
            <field name="arch" type="xml">
                <xpath expr="//field[@name= 'wage']" position="after">
                    <field name = "gov_fees" optional="hide"/>
                    <field name = "insurance" optional="hide"/>
                    <field name = "transport" optional="hide"/>
                    <field name = "housing" optional="hide"/>
                    <field name = "substance" optional="hide"/>
                </xpath>
            </field>
        </record>
    </data>
</odoo>